pandas_smartcols-0.1.1.dist-info/licenses/LICENSE
smartcols/__init__.py
smartcols/__version__.py
smartcols/core.py
pandas_smartcols-0.1.1.dist-info/METADATA
pandas_smartcols-0.1.1.dist-info/WHEEL
pandas_smartcols-0.1.1.dist-info/top_level.txt
pandas_smartcols-0.1.1.dist-info/RECORD
