Metadata-Version: 2.4
Name: pandas-smartcols
Version: 0.1.1
Summary: Pandas column manipulation toolkit
Author: Dinis Esteves
Project-URL: Homepage, https://github.com/Dinis-Esteves/pandas-smartcols
Project-URL: Bug Tracker, https://github.com/Dinis-Esteves/pandas-smartcols/issues
Project-URL: Source Code, https://github.com/Dinis-Esteves/pandas-smartcols
Requires-Python: >=3.9
License-File: LICENSE
Requires-Dist: pandas>=2.0
Requires-Dist: numpy>=1.24
Dynamic: license-file
